flixr/__init__.py
flixr/__main__.py
flixr/api.py
flixr/display.py
flixr/interface.py
flixr-0.0.1.dist-info/LICENSE
flixr-0.0.1.dist-info/METADATA
flixr-0.0.1.dist-info/WHEEL
flixr-0.0.1.dist-info/entry_points.txt
flixr-0.0.1.dist-info/top_level.txt
flixr-0.0.1.dist-info/RECORD
