Metadata-Version: 2.1
Name: flixr
Version: 0.0.1
Summary: A command line utility for television show information.
Home-page: https://github.com/kelvindecosta/flixr
Author: Kelvin DeCosta
Author-email: decostakelvin@gmail.com
License: MIT
Platform: UNKNOWN
Classifier: Programming Language :: Python :: 3
Classifier: License :: OSI Approved :: MIT License
Classifier: Operating System :: OS Independent
Requires-Python: >=3.6
Requires-Dist: sty
